pypersist/__init__.py
pypersist/commoncache.py
pypersist/diskcache.py
pypersist/hashing.py
pypersist/mongodbcache.py
pypersist/pickling.py
pypersist/preprocessing.py
pypersist-1.1.dist-info/LICENSE
pypersist-1.1.dist-info/METADATA
pypersist-1.1.dist-info/WHEEL
pypersist-1.1.dist-info/top_level.txt
pypersist-1.1.dist-info/RECORD
