Metadata-Version: 2.1
Name: pypersist
Version: 1.1
Summary: Persistent memoisation framework for Python
Home-page: https://github.com/mtorpey/pypersist
Author: Michael Torpey
Author-email: mct25@st-andrews.ac.uk
License: GPL
Platform: UNKNOWN
Classifier: Programming Language :: Python :: 2.7
Classifier: Programming Language :: Python :: 3
Classifier: License :: OSI Approved :: GNU General Public License (GPL)
Classifier: Operating System :: OS Independent
Requires-Dist: requests
